openai_client/__init__.py
openai_client/base/__init__.py
openai_client/base/client.py
openai_client/base/image_client.py
openai_client/clients/__init__.py
openai_client/clients/chatbot/__init__.py
openai_client/clients/chatbot/client.py
openai_client/clients/completion/__init__.py
openai_client/clients/completion/client.py
openai_client/clients/images/__init__.py
openai_client/clients/images/clients/__init__.py
openai_client/clients/images/clients/create_image.py
openai_client/clients/images/clients/edit_image.py
openai_client/clients/images/clients/image_variation.py
openai_client/enums/__init__.py
openai_client/enums/base.py
openai_client/enums/image_response_formats.py
openai_client/enums/image_sizes.py
openai_client/enums/models.py
openai_client/enums/roles.py
openai_client/mixins/__init__.py
openai_client/mixins/chat_context_manager.py
openai_client/mixins/example_context_manager.py
openai_client/mixins/image_context_manager.py
OpenAI_API_Python_Client-1.0.15.dist-info/LICENSE
OpenAI_API_Python_Client-1.0.15.dist-info/METADATA
OpenAI_API_Python_Client-1.0.15.dist-info/WHEEL
OpenAI_API_Python_Client-1.0.15.dist-info/top_level.txt
OpenAI_API_Python_Client-1.0.15.dist-info/RECORD
