Metadata-Version: 2.1
Name: OpenAI-API-Python-Client
Version: 1.0.15
Summary: A base client for interacting with the OpenAI API and custom clients/mixins to make developing things like chatbots super quick!
Home-page: https://github.com/Topazoo/OpenAI-Python-Client
Maintainer: Peter Swanson
Project-URL: Bug Tracker, https://github.com/Topazoo/OpenAI-Python-Client/issues
Project-URL: Changelog, https://github.com/Topazoo/OpenAI-Python-Client/releases
Classifier: Programming Language :: Python :: 3
Classifier: License :: OSI Approved :: BSD License
Classifier: Intended Audience :: Developers
License-File: LICENSE
Requires-Dist: openai (>=0.27.0)
